everysk/__init__.py
everysk/_version.py
everysk/config.py
everysk/settings.py
everysk/tests.py
everysk/utils.py
everysk/version.py
everysk/api/__init__.py
everysk/api/api_requestor.py
everysk/api/http_client.py
everysk/api/tests.py
everysk/api/utils.py
everysk/api/api_resources/__init__.py
everysk/api/api_resources/api_resource.py
everysk/api/api_resources/calculation.py
everysk/api/api_resources/custom_index.py
everysk/api/api_resources/datastore.py
everysk/api/api_resources/file.py
everysk/api/api_resources/market_data.py
everysk/api/api_resources/parser.py
everysk/api/api_resources/portfolio.py
everysk/api/api_resources/private_security.py
everysk/api/api_resources/report.py
everysk/api/api_resources/report_template.py
everysk/api/api_resources/tests.py
everysk/api/api_resources/worker_execution.py
everysk/api/api_resources/workflow.py
everysk/api/api_resources/workflow_execution.py
everysk/api/api_resources/workspace.py
everysk/core/compress.py
everysk/core/exceptions.py
everysk/core/fields.py
everysk/core/firestore.py
everysk/core/http.py
everysk/core/lists.py
everysk/core/log.py
everysk/core/number.py
everysk/core/object.py
everysk/core/redis.py
everysk/core/retry.py
everysk/core/serialize.py
everysk/core/sftp.py
everysk/core/signing.py
everysk/core/slack.py
everysk/core/string.py
everysk/core/tests.py
everysk/core/threads.py
everysk/core/undefined.py
everysk/core/unittests.py
everysk/core/workers.py
everysk/core/_tests/serialize/test_json.py
everysk/core/_tests/serialize/test_orjson.py
everysk/core/_tests/serialize/test_pickle.py
everysk/core/cloud_function/main.py
everysk/core/cloud_function/tests.py
everysk/core/datetime/__init__.py
everysk/core/datetime/calendar.py
everysk/core/datetime/date.py
everysk/core/datetime/date_expression.py
everysk/core/datetime/date_mixin.py
everysk/core/datetime/date_settings.py
everysk/core/datetime/datetime.py
everysk/core/fixtures/_settings.py
everysk_lib-1.10.0.dist-info/.gitignore
everysk_lib-1.10.0.dist-info/METADATA
everysk_lib-1.10.0.dist-info/WHEEL
everysk_lib-1.10.0.dist-info/top_level.txt
everysk_lib-1.10.0.dist-info/RECORD
everysk_lib-1.10.0.dist-info/licenses/LICENSE.txt
