Metadata-Version: 2.4
Name: everysk-lib
Version: 1.10.0
Summary: Generic lib to share python code on Everysk.
License-Expression: LicenseRef-Proprietary
Project-URL: Homepage, https://everysk.com/
Keywords: python,development,lib
Classifier: Development Status :: 5 - Production/Stable
Classifier: Intended Audience :: Developers
Classifier: Topic :: Software Development :: Build Tools
Classifier: Programming Language :: Python :: 3.11
Requires-Python: >=3.11
License-File: LICENSE.txt
Requires-Dist: python-dateutil<=3.0.0,>=2.8.2
Requires-Dist: holidays==0.51
Requires-Dist: tzdata<=2025.2,>=2024.1
Provides-Extra: requests
Requires-Dist: certifi==2025.10.5; extra == "requests"
Requires-Dist: charset_normalizer==3.4.4; extra == "requests"
Requires-Dist: idna==3.11; extra == "requests"
Requires-Dist: urllib3==2.6.3; extra == "requests"
Requires-Dist: requests==2.32.5; extra == "requests"
Provides-Extra: firestore
Requires-Dist: certifi==2025.10.5; extra == "firestore"
Requires-Dist: charset-normalizer==3.3.2; extra == "firestore"
Requires-Dist: idna==3.6; extra == "firestore"
Requires-Dist: urllib3==2.6.3; extra == "firestore"
Requires-Dist: requests==2.32.4; extra == "firestore"
Requires-Dist: pyasn1==0.5.1; extra == "firestore"
Requires-Dist: pyasn1-modules==0.3.0; extra == "firestore"
Requires-Dist: cachetools==5.3.2; extra == "firestore"
Requires-Dist: rsa==4.9; extra == "firestore"
Requires-Dist: google-auth==2.28.1; extra == "firestore"
Requires-Dist: googleapis-common-protos==1.62.0; extra == "firestore"
Requires-Dist: grpcio==1.60.1; extra == "firestore"
Requires-Dist: grpcio-status==1.60.1; extra == "firestore"
Requires-Dist: google-api-core[grpc]==2.17.1; extra == "firestore"
Requires-Dist: google-cloud-core==2.4.1; extra == "firestore"
Requires-Dist: proto-plus==1.23.0; extra == "firestore"
Requires-Dist: protobuf==4.25.8; extra == "firestore"
Requires-Dist: google-cloud-firestore==2.15.0; extra == "firestore"
Provides-Extra: redis
Requires-Dist: hiredis==3.3.0; extra == "redis"
Requires-Dist: redis==7.0.0; extra == "redis"
Provides-Extra: tasks
Requires-Dist: certifi==2025.10.5; extra == "tasks"
Requires-Dist: charset-normalizer==3.3.2; extra == "tasks"
Requires-Dist: idna==3.6; extra == "tasks"
Requires-Dist: urllib3==2.6.3; extra == "tasks"
Requires-Dist: requests==2.32.4; extra == "tasks"
Requires-Dist: pyasn1==0.5.1; extra == "tasks"
Requires-Dist: pyasn1-modules==0.3.0; extra == "tasks"
Requires-Dist: cachetools==5.3.2; extra == "tasks"
Requires-Dist: rsa==4.9; extra == "tasks"
Requires-Dist: google-auth==2.28.1; extra == "tasks"
Requires-Dist: googleapis-common-protos==1.62.0; extra == "tasks"
Requires-Dist: grpcio==1.60.1; extra == "tasks"
Requires-Dist: grpcio-status==1.60.1; extra == "tasks"
Requires-Dist: google-api-core[grpc]==2.17.1; extra == "tasks"
Requires-Dist: google-cloud-core==2.4.1; extra == "tasks"
Requires-Dist: proto-plus==1.23.0; extra == "tasks"
Requires-Dist: protobuf==4.25.8; extra == "tasks"
Requires-Dist: grpc-google-iam-v1==0.13.0; extra == "tasks"
Requires-Dist: google-cloud-tasks==2.16.1; extra == "tasks"
Provides-Extra: flask
Requires-Dist: MarkupSafe==2.1.5; extra == "flask"
Requires-Dist: blinker==1.8.2; extra == "flask"
Requires-Dist: click==8.1.7; extra == "flask"
Requires-Dist: itsdangerous==2.2.0; extra == "flask"
Requires-Dist: Jinja2==3.1.6; extra == "flask"
Requires-Dist: Werkzeug==3.0.3; extra == "flask"
Requires-Dist: flask==3.0.3; extra == "flask"
Provides-Extra: starlette
Requires-Dist: idna==3.10; extra == "starlette"
Requires-Dist: sniffio==1.3.1; extra == "starlette"
Requires-Dist: typing-extensions==4.15.0; extra == "starlette"
Requires-Dist: anyio==4.9.0; extra == "starlette"
Requires-Dist: certifi==2025.10.5; extra == "starlette"
Requires-Dist: h11==0.16.0; extra == "starlette"
Requires-Dist: httpcore==1.0.9; extra == "starlette"
Requires-Dist: hpack==4.1.0; extra == "starlette"
Requires-Dist: hyperframe==6.1.0; extra == "starlette"
Requires-Dist: h2==4.3.0; extra == "starlette"
Requires-Dist: httpx==0.28.1; extra == "starlette"
Requires-Dist: MarkupSafe==3.0.2; extra == "starlette"
Requires-Dist: jinja2==3.1.6; extra == "starlette"
Requires-Dist: itsdangerous==2.2.0; extra == "starlette"
Requires-Dist: python-multipart==0.0.20; extra == "starlette"
Requires-Dist: pyyaml==6.0.3; extra == "starlette"
Requires-Dist: starlette==0.49.1; extra == "starlette"
Provides-Extra: httpx
Requires-Dist: idna==3.10; extra == "httpx"
Requires-Dist: sniffio==1.3.1; extra == "httpx"
Requires-Dist: typing-extensions==4.15.0; extra == "httpx"
Requires-Dist: anyio==4.9.0; extra == "httpx"
Requires-Dist: certifi==2025.10.5; extra == "httpx"
Requires-Dist: h11==0.16.0; extra == "httpx"
Requires-Dist: httpcore==1.0.9; extra == "httpx"
Requires-Dist: hpack==4.1.0; extra == "httpx"
Requires-Dist: hyperframe==6.1.0; extra == "httpx"
Requires-Dist: h2==4.3.0; extra == "httpx"
Requires-Dist: httpx==0.28.1; extra == "httpx"
Provides-Extra: paramiko
Requires-Dist: bcrypt==4.2.0; extra == "paramiko"
Requires-Dist: pycparser==2.22; extra == "paramiko"
Requires-Dist: cffi==1.17.1; extra == "paramiko"
Requires-Dist: cryptography==44.0.1; extra == "paramiko"
Requires-Dist: pynacl==1.5.0; extra == "paramiko"
Requires-Dist: paramiko==3.5.0; extra == "paramiko"
Provides-Extra: everysk-orjson
Requires-Dist: everysk-orjson==3.11.3; extra == "everysk-orjson"
Provides-Extra: expression
Requires-Dist: lark==1.2.2; extra == "expression"
Requires-Dist: numpy==1.26.4; extra == "expression"
Requires-Dist: pandas==2.1.4; extra == "expression"
Provides-Extra: postgresql
Requires-Dist: psycopg-binary==3.3.0; extra == "postgresql"
Requires-Dist: psycopg-pool==3.3.0; extra == "postgresql"
Requires-Dist: psycopg==3.3.0; extra == "postgresql"
Dynamic: license-file
